cvttf_NotoSansCJK_Thin/NotoSansCJKtc-Thin.otf
cvttf_NotoSansCJK_Thin/__init__.py
cvttf_NotoSansCJK_Thin-1.0.data/data/NotoSansCJKtc-Thin.otf
cvttf_NotoSansCJK_Thin-1.0.dist-info/DESCRIPTION.rst
cvttf_NotoSansCJK_Thin-1.0.dist-info/METADATA
cvttf_NotoSansCJK_Thin-1.0.dist-info/RECORD
cvttf_NotoSansCJK_Thin-1.0.dist-info/WHEEL
cvttf_NotoSansCJK_Thin-1.0.dist-info/metadata.json
cvttf_NotoSansCJK_Thin-1.0.dist-info/top_level.txt
